{
    "@context": "http://iiif.io/api/presentation/2/context.json",
    "@id": "https://readux.ecdsdev.org/iiif/v2/2qchts23/list/2qchts23_00000054.jpg",
    "@type": "sc:AnnotationList",
    "resources": [
        {
            "@context": "http://iiif.io/api/presentation/2/context.json",
            "@id": "f593c2f2-4657-453f-99fb-f23e90b6c294",
            "@type": "oa:Annotation",
            "motivation": "sc:painting",
            "annotatedBy": {
                "name": "OCR"
            },
            "resource": {
                "@type": "cnt:ContentAsText",
                "format": "text/html",
                "chars": "<span id='f593c2f2-4657-453f-99fb-f23e90b6c294' class='anno-f593c2f2-4657-453f-99fb-f23e90b6c294' data-letter-spacing='-0.16079545454545455'>Scala</span>",
                "language": "en"
            },
            "on": {
                "full": "https://readux.ecdsdev.org/iiif/v2/2qchts23/canvas/2qchts23_00000054.jpg",
                "@type": "oa:SpecificResource",
                "within": {
                    "@id": "https://readux.ecdsdev.org/iiif/v2/2qchts23/manifest",
                    "@type": "sc:Manifest"
                },
                "selector": {
                    "@type": "oa:FragmentSelector",
                    "value": "xywh=1396,4120,110,127",
                    "item": {
                        "@type": "oa:FragmentSelector"
                    }
                }
            },
            "stylesheet": {
                "type": "CssStylesheet",
                "value": ".anno-f593c2f2-4657-453f-99fb-f23e90b6c294: { height: 127px; width: 110px; font-size: 79.375px; letter-spacing: -17.6875px;}"
            }
        },
        {
            "@context": "http://iiif.io/api/presentation/2/context.json",
            "@id": "ef5c2973-dbf7-45d5-95b8-10eb89c405d0",
            "@type": "oa:Annotation",
            "motivation": "sc:painting",
            "annotatedBy": {
                "name": "OCR"
            },
            "resource": {
                "@type": "cnt:ContentAsText",
                "format": "text/html",
                "chars": "<span id='ef5c2973-dbf7-45d5-95b8-10eb89c405d0' class='anno-ef5c2973-dbf7-45d5-95b8-10eb89c405d0' data-letter-spacing='-0.5056306306306306'>palmorum</span>",
                "language": "en"
            },
            "on": {
                "full": "https://readux.ecdsdev.org/iiif/v2/2qchts23/canvas/2qchts23_00000054.jpg",
                "@type": "oa:SpecificResource",
                "within": {
                    "@id": "https://readux.ecdsdev.org/iiif/v2/2qchts23/manifest",
                    "@type": "sc:Manifest"
                },
                "selector": {
                    "@type": "oa:FragmentSelector",
                    "value": "xywh=1389,4345,111,224",
                    "item": {
                        "@type": "oa:FragmentSelector"
                    }
                }
            },
            "stylesheet": {
                "type": "CssStylesheet",
                "value": ".anno-ef5c2973-dbf7-45d5-95b8-10eb89c405d0: { height: 224px; width: 111px; font-size: 140.0px; letter-spacing: -56.125px;}"
            }
        },
        {
            "@context": "http://iiif.io/api/presentation/2/context.json",
            "@id": "b51f1355-0478-4641-a6dc-9a33597e9f61",
            "@type": "oa:Annotation",
            "motivation": "sc:painting",
            "annotatedBy": {
                "name": "OCR"
            },
            "resource": {
                "@type": "cnt:ContentAsText",
                "format": "text/html",
                "chars": "<span id='b51f1355-0478-4641-a6dc-9a33597e9f61' class='anno-b51f1355-0478-4641-a6dc-9a33597e9f61' data-letter-spacing='-1.1019794400699912'>VESTIGIVM</span>",
                "language": "en"
            },
            "on": {
                "full": "https://readux.ecdsdev.org/iiif/v2/2qchts23/canvas/2qchts23_00000054.jpg",
                "@type": "oa:SpecificResource",
                "within": {
                    "@id": "https://readux.ecdsdev.org/iiif/v2/2qchts23/manifest",
                    "@type": "sc:Manifest"
                },
                "selector": {
                    "@type": "oa:FragmentSelector",
                    "value": "xywh=1230,2506,127,493",
                    "item": {
                        "@type": "oa:FragmentSelector"
                    }
                }
            },
            "stylesheet": {
                "type": "CssStylesheet",
                "value": ".anno-b51f1355-0478-4641-a6dc-9a33597e9f61: { height: 493px; width: 127px; font-size: 308.125px; letter-spacing: -139.95138888888889px;}"
            }
        },
        {
            "@context": "http://iiif.io/api/presentation/2/context.json",
            "@id": "4535a2d5-72ca-4541-a1d3-4d66e6430e2f",
            "@type": "oa:Annotation",
            "motivation": "sc:painting",
            "annotatedBy": {
                "name": "OCR"
            },
            "resource": {
                "@type": "cnt:ContentAsText",
                "format": "text/html",
                "chars": "<span id='4535a2d5-72ca-4541-a1d3-4d66e6430e2f' class='anno-4535a2d5-72ca-4541-a1d3-4d66e6430e2f' data-letter-spacing='-0.6593992248062015'>TEMPLI</span>",
                "language": "en"
            },
            "on": {
                "full": "https://readux.ecdsdev.org/iiif/v2/2qchts23/canvas/2qchts23_00000054.jpg",
                "@type": "oa:SpecificResource",
                "within": {
                    "@id": "https://readux.ecdsdev.org/iiif/v2/2qchts23/manifest",
                    "@type": "sc:Manifest"
                },
                "selector": {
                    "@type": "oa:FragmentSelector",
                    "value": "xywh=1230,3105,129,341",
                    "item": {
                        "@type": "oa:FragmentSelector"
                    }
                }
            },
            "stylesheet": {
                "type": "CssStylesheet",
                "value": ".anno-4535a2d5-72ca-4541-a1d3-4d66e6430e2f: { height: 341px; width: 129px; font-size: 213.125px; letter-spacing: -85.0625px;}"
            }
        },
        {
            "@context": "http://iiif.io/api/presentation/2/context.json",
            "@id": "ebcff80a-a775-4070-9470-8b7a63ed8348",
            "@type": "oa:Annotation",
            "motivation": "sc:painting",
            "annotatedBy": {
                "name": "OCR"
            },
            "resource": {
                "@type": "cnt:ContentAsText",
                "format": "text/html",
                "chars": "<span id='ebcff80a-a775-4070-9470-8b7a63ed8348' class='anno-ebcff80a-a775-4070-9470-8b7a63ed8348' data-letter-spacing='0.27608267716535434'>S.</span>",
                "language": "en"
            },
            "on": {
                "full": "https://readux.ecdsdev.org/iiif/v2/2qchts23/canvas/2qchts23_00000054.jpg",
                "@type": "oa:SpecificResource",
                "within": {
                    "@id": "https://readux.ecdsdev.org/iiif/v2/2qchts23/manifest",
                    "@type": "sc:Manifest"
                },
                "selector": {
                    "@type": "oa:FragmentSelector",
                    "value": "xywh=1228,3507,127,91",
                    "item": {
                        "@type": "oa:FragmentSelector"
                    }
                }
            },
            "stylesheet": {
                "type": "CssStylesheet",
                "value": ".anno-ebcff80a-a775-4070-9470-8b7a63ed8348: { height: 91px; width: 127px; font-size: 56.875px; letter-spacing: 35.0625px;}"
            }
        },
        {
            "@context": "http://iiif.io/api/presentation/2/context.json",
            "@id": "e8f2f033-ae7e-4ba6-a8be-53c62e457ba9",
            "@type": "oa:Annotation",
            "motivation": "sc:painting",
            "annotatedBy": {
                "name": "OCR"
            },
            "resource": {
                "@type": "cnt:ContentAsText",
                "format": "text/html",
                "chars": "<span id='e8f2f033-ae7e-4ba6-a8be-53c62e457ba9' class='anno-e8f2f033-ae7e-4ba6-a8be-53c62e457ba9' data-letter-spacing='-0.7659120734908136'>ANDREA</span>",
                "language": "en"
            },
            "on": {
                "full": "https://readux.ecdsdev.org/iiif/v2/2qchts23/canvas/2qchts23_00000054.jpg",
                "@type": "oa:SpecificResource",
                "within": {
                    "@id": "https://readux.ecdsdev.org/iiif/v2/2qchts23/manifest",
                    "@type": "sc:Manifest"
                },
                "selector": {
                    "@type": "oa:FragmentSelector",
                    "value": "xywh=1228,3643,127,379",
                    "item": {
                        "@type": "oa:FragmentSelector"
                    }
                }
            },
            "stylesheet": {
                "type": "CssStylesheet",
                "value": ".anno-e8f2f033-ae7e-4ba6-a8be-53c62e457ba9: { height: 379px; width: 127px; font-size: 236.875px; letter-spacing: -97.27083333333333px;}"
            }
        },
        {
            "@context": "http://iiif.io/api/presentation/2/context.json",
            "@id": "c06428e0-b1f6-49f6-8f4a-9ef18bd54ed2",
            "@type": "oa:Annotation",
            "motivation": "sc:painting",
            "annotatedBy": {
                "name": "OCR"
            },
            "resource": {
                "@type": "cnt:ContentAsText",
                "format": "text/html",
                "chars": "<span id='c06428e0-b1f6-49f6-8f4a-9ef18bd54ed2' class='anno-c06428e0-b1f6-49f6-8f4a-9ef18bd54ed2' data-letter-spacing='-1.0044291338582678'>APOSTOLI</span>",
                "language": "en"
            },
            "on": {
                "full": "https://readux.ecdsdev.org/iiif/v2/2qchts23/canvas/2qchts23_00000054.jpg",
                "@type": "oa:SpecificResource",
                "within": {
                    "@id": "https://readux.ecdsdev.org/iiif/v2/2qchts23/manifest",
                    "@type": "sc:Manifest"
                },
                "selector": {
                    "@type": "oa:FragmentSelector",
                    "value": "xywh=1228,4145,127,459",
                    "item": {
                        "@type": "oa:FragmentSelector"
                    }
                }
            },
            "stylesheet": {
                "type": "CssStylesheet",
                "value": ".anno-c06428e0-b1f6-49f6-8f4a-9ef18bd54ed2: { height: 459px; width: 127px; font-size: 286.875px; letter-spacing: -127.5625px;}"
            }
        },
        {
            "@context": "http://iiif.io/api/presentation/2/context.json",
            "@id": "8c9428bc-8112-43af-8667-babf8f12e242",
            "@type": "oa:Annotation",
            "motivation": "sc:painting",
            "annotatedBy": {
                "name": "OCR"
            },
            "resource": {
                "@type": "cnt:ContentAsText",
                "format": "text/html",
                "chars": "<span id='8c9428bc-8112-43af-8667-babf8f12e242' class='anno-8c9428bc-8112-43af-8667-babf8f12e242' data-letter-spacing='-0.6576443569553806'>SOCIET</span>",
                "language": "en"
            },
            "on": {
                "full": "https://readux.ecdsdev.org/iiif/v2/2qchts23/canvas/2qchts23_00000054.jpg",
                "@type": "oa:SpecificResource",
                "within": {
                    "@id": "https://readux.ecdsdev.org/iiif/v2/2qchts23/manifest",
                    "@type": "sc:Manifest"
                },
                "selector": {
                    "@type": "oa:FragmentSelector",
                    "value": "xywh=1226,4698,127,335",
                    "item": {
                        "@type": "oa:FragmentSelector"
                    }
                }
            },
            "stylesheet": {
                "type": "CssStylesheet",
                "value": ".anno-8c9428bc-8112-43af-8667-babf8f12e242: { height: 335px; width: 127px; font-size: 209.375px; letter-spacing: -83.52083333333333px;}"
            }
        },
        {
            "@context": "http://iiif.io/api/presentation/2/context.json",
            "@id": "c9242db0-2373-42a4-900b-6fa526663cd6",
            "@type": "oa:Annotation",
            "motivation": "sc:painting",
            "annotatedBy": {
                "name": "OCR"
            },
            "resource": {
                "@type": "cnt:ContentAsText",
                "format": "text/html",
                "chars": "<span id='c9242db0-2373-42a4-900b-6fa526663cd6' class='anno-c9242db0-2373-42a4-900b-6fa526663cd6' data-letter-spacing='0.9138779527559056'>.</span>",
                "language": "en"
            },
            "on": {
                "full": "https://readux.ecdsdev.org/iiif/v2/2qchts23/canvas/2qchts23_00000054.jpg",
                "@type": "oa:SpecificResource",
                "within": {
                    "@id": "https://readux.ecdsdev.org/iiif/v2/2qchts23/manifest",
                    "@type": "sc:Manifest"
                },
                "selector": {
                    "@type": "oa:FragmentSelector",
                    "value": "xywh=1226,5041,127,35",
                    "item": {
                        "@type": "oa:FragmentSelector"
                    }
                }
            },
            "stylesheet": {
                "type": "CssStylesheet",
                "value": ".anno-c9242db0-2373-42a4-900b-6fa526663cd6: { height: 35px; width: 127px; font-size: 21.875px; letter-spacing: 116.0625px;}"
            }
        },
        {
            "@context": "http://iiif.io/api/presentation/2/context.json",
            "@id": "f226b34b-f0dd-4e19-aa05-2e66182d0613",
            "@type": "oa:Annotation",
            "motivation": "sc:painting",
            "annotatedBy": {
                "name": "OCR"
            },
            "resource": {
                "@type": "cnt:ContentAsText",
                "format": "text/html",
                "chars": "<span id='f226b34b-f0dd-4e19-aa05-2e66182d0613' class='anno-f226b34b-f0dd-4e19-aa05-2e66182d0613' data-letter-spacing='-0.40285433070866145'>IESVS</span>",
                "language": "en"
            },
            "on": {
                "full": "https://readux.ecdsdev.org/iiif/v2/2qchts23/canvas/2qchts23_00000054.jpg",
                "@type": "oa:SpecificResource",
                "within": {
                    "@id": "https://readux.ecdsdev.org/iiif/v2/2qchts23/manifest",
                    "@type": "sc:Manifest"
                },
                "selector": {
                    "@type": "oa:FragmentSelector",
                    "value": "xywh=1226,5135,127,245",
                    "item": {
                        "@type": "oa:FragmentSelector"
                    }
                }
            },
            "stylesheet": {
                "type": "CssStylesheet",
                "value": ".anno-f226b34b-f0dd-4e19-aa05-2e66182d0613: { height: 245px; width: 127px; font-size: 153.125px; letter-spacing: -51.1625px;}"
            }
        },
        {
            "@context": "http://iiif.io/api/presentation/2/context.json",
            "@id": "dad99574-61e2-42b3-9794-8fdf0146fba2",
            "@type": "oa:Annotation",
            "motivation": "sc:painting",
            "annotatedBy": {
                "name": "OCR"
            },
            "resource": {
                "@type": "cnt:ContentAsText",
                "format": "text/html",
                "chars": "<span id='dad99574-61e2-42b3-9794-8fdf0146fba2' class='anno-dad99574-61e2-42b3-9794-8fdf0146fba2' data-letter-spacing='0.38188976377952755'>IN</span>",
                "language": "en"
            },
            "on": {
                "full": "https://readux.ecdsdev.org/iiif/v2/2qchts23/canvas/2qchts23_00000054.jpg",
                "@type": "oa:SpecificResource",
                "within": {
                    "@id": "https://readux.ecdsdev.org/iiif/v2/2qchts23/manifest",
                    "@type": "sc:Manifest"
                },
                "selector": {
                    "@type": "oa:FragmentSelector",
                    "value": "xywh=1226,5497,127,48",
                    "item": {
                        "@type": "oa:FragmentSelector"
                    }
                }
            },
            "stylesheet": {
                "type": "CssStylesheet",
                "value": ".anno-dad99574-61e2-42b3-9794-8fdf0146fba2: { height: 48px; width: 127px; font-size: 30.0px; letter-spacing: 48.5px;}"
            }
        },
        {
            "@context": "http://iiif.io/api/presentation/2/context.json",
            "@id": "e85e0e34-4e1a-4a0c-8c8d-2e7bbca0eb6c",
            "@type": "oa:Annotation",
            "motivation": "sc:painting",
            "annotatedBy": {
                "name": "OCR"
            },
            "resource": {
                "@type": "cnt:ContentAsText",
                "format": "text/html",
                "chars": "<span id='e85e0e34-4e1a-4a0c-8c8d-2e7bbca0eb6c' class='anno-e85e0e34-4e1a-4a0c-8c8d-2e7bbca0eb6c' data-letter-spacing='-1.1921834625322996'>QVIRINALL</span>",
                "language": "en"
            },
            "on": {
                "full": "https://readux.ecdsdev.org/iiif/v2/2qchts23/canvas/2qchts23_00000054.jpg",
                "@type": "oa:SpecificResource",
                "within": {
                    "@id": "https://readux.ecdsdev.org/iiif/v2/2qchts23/manifest",
                    "@type": "sc:Manifest"
                },
                "selector": {
                    "@type": "oa:FragmentSelector",
                    "value": "xywh=1226,5654,129,538",
                    "item": {
                        "@type": "oa:FragmentSelector"
                    }
                }
            },
            "stylesheet": {
                "type": "CssStylesheet",
                "value": ".anno-e85e0e34-4e1a-4a0c-8c8d-2e7bbca0eb6c: { height: 538px; width: 129px; font-size: 336.25px; letter-spacing: -153.79166666666666px;}"
            }
        },
        {
            "@context": "http://iiif.io/api/presentation/2/context.json",
            "@id": "6697767d-cb87-4a3c-9e98-536510475ee4",
            "@type": "oa:Annotation",
            "motivation": "sc:painting",
            "annotatedBy": {
                "name": "OCR"
            },
            "resource": {
                "@type": "cnt:ContentAsText",
                "format": "text/html",
                "chars": "<span id='6697767d-cb87-4a3c-9e98-536510475ee4' class='anno-6697767d-cb87-4a3c-9e98-536510475ee4' data-letter-spacing='0.9114173228346457'>.</span>",
                "language": "en"
            },
            "on": {
                "full": "https://readux.ecdsdev.org/iiif/v2/2qchts23/canvas/2qchts23_00000054.jpg",
                "@type": "oa:SpecificResource",
                "within": {
                    "@id": "https://readux.ecdsdev.org/iiif/v2/2qchts23/manifest",
                    "@type": "sc:Manifest"
                },
                "selector": {
                    "@type": "oa:FragmentSelector",
                    "value": "xywh=1224,6186,127,36",
                    "item": {
                        "@type": "oa:FragmentSelector"
                    }
                }
            },
            "stylesheet": {
                "type": "CssStylesheet",
                "value": ".anno-6697767d-cb87-4a3c-9e98-536510475ee4: { height: 36px; width: 127px; font-size: 22.5px; letter-spacing: 115.75px;}"
            }
        },
        {
            "@context": "http://iiif.io/api/presentation/2/context.json",
            "@id": "82e2fe4f-1257-4afc-965d-3d201d974482",
            "@type": "oa:Annotation",
            "motivation": "sc:painting",
            "annotatedBy": {
                "name": "OCR"
            },
            "resource": {
                "@type": "cnt:ContentAsText",
                "format": "text/html",
                "chars": "<span id='82e2fe4f-1257-4afc-965d-3d201d974482' class='anno-82e2fe4f-1257-4afc-965d-3d201d974482' data-letter-spacing='0.21185064935064934'>Eq</span>",
                "language": "en"
            },
            "on": {
                "full": "https://readux.ecdsdev.org/iiif/v2/2qchts23/canvas/2qchts23_00000054.jpg",
                "@type": "oa:SpecificResource",
                "within": {
                    "@id": "https://readux.ecdsdev.org/iiif/v2/2qchts23/manifest",
                    "@type": "sc:Manifest"
                },
                "selector": {
                    "@type": "oa:FragmentSelector",
                    "value": "xywh=1101,3773,77,71",
                    "item": {
                        "@type": "oa:FragmentSelector"
                    }
                }
            },
            "stylesheet": {
                "type": "CssStylesheet",
                "value": ".anno-82e2fe4f-1257-4afc-965d-3d201d974482: { height: 71px; width: 77px; font-size: 44.375px; letter-spacing: 16.3125px;}"
            }
        },
        {
            "@context": "http://iiif.io/api/presentation/2/context.json",
            "@id": "08e660f7-6e30-4993-9596-b1b9e022923d",
            "@type": "oa:Annotation",
            "motivation": "sc:painting",
            "annotatedBy": {
                "name": "OCR"
            },
            "resource": {
                "@type": "cnt:ContentAsText",
                "format": "text/html",
                "chars": "<span id='08e660f7-6e30-4993-9596-b1b9e022923d' class='anno-08e660f7-6e30-4993-9596-b1b9e022923d' data-letter-spacing='0.9107142857142857'>.</span>",
                "language": "en"
            },
            "on": {
                "full": "https://readux.ecdsdev.org/iiif/v2/2qchts23/canvas/2qchts23_00000054.jpg",
                "@type": "oa:SpecificResource",
                "within": {
                    "@id": "https://readux.ecdsdev.org/iiif/v2/2qchts23/manifest",
                    "@type": "sc:Manifest"
                },
                "selector": {
                    "@type": "oa:FragmentSelector",
                    "value": "xywh=1101,3850,77,22",
                    "item": {
                        "@type": "oa:FragmentSelector"
                    }
                }
            },
            "stylesheet": {
                "type": "CssStylesheet",
                "value": ".anno-08e660f7-6e30-4993-9596-b1b9e022923d: { height: 22px; width: 77px; font-size: 13.75px; letter-spacing: 70.125px;}"
            }
        },
        {
            "@context": "http://iiif.io/api/presentation/2/context.json",
            "@id": "a3e6ea3a-9aa2-46eb-bf49-cbcd60b7cb88",
            "@type": "oa:Annotation",
            "motivation": "sc:painting",
            "annotatedBy": {
                "name": "OCR"
            },
            "resource": {
                "@type": "cnt:ContentAsText",
                "format": "text/html",
                "chars": "<span id='a3e6ea3a-9aa2-46eb-bf49-cbcd60b7cb88' class='anno-a3e6ea3a-9aa2-46eb-bf49-cbcd60b7cb88' data-letter-spacing='0.25833333333333336'>1o</span>",
                "language": "en"
            },
            "on": {
                "full": "https://readux.ecdsdev.org/iiif/v2/2qchts23/canvas/2qchts23_00000054.jpg",
                "@type": "oa:SpecificResource",
                "within": {
                    "@id": "https://readux.ecdsdev.org/iiif/v2/2qchts23/manifest",
                    "@type": "sc:Manifest"
                },
                "selector": {
                    "@type": "oa:FragmentSelector",
                    "value": "xywh=1101,3902,75,58",
                    "item": {
                        "@type": "oa:FragmentSelector"
                    }
                }
            },
            "stylesheet": {
                "type": "CssStylesheet",
                "value": ".anno-a3e6ea3a-9aa2-46eb-bf49-cbcd60b7cb88: { height: 58px; width: 75px; font-size: 36.25px; letter-spacing: 19.375px;}"
            }
        },
        {
            "@context": "http://iiif.io/api/presentation/2/context.json",
            "@id": "8831d304-ed55-4b6a-9326-cbea343a9d15",
            "@type": "oa:Annotation",
            "motivation": "sc:painting",
            "annotatedBy": {
                "name": "OCR"
            },
            "resource": {
                "@type": "cnt:ContentAsText",
                "format": "text/html",
                "chars": "<span id='8831d304-ed55-4b6a-9326-cbea343a9d15' class='anno-8831d304-ed55-4b6a-9326-cbea343a9d15' data-letter-spacing='0.9107142857142857'>:</span>",
                "language": "en"
            },
            "on": {
                "full": "https://readux.ecdsdev.org/iiif/v2/2qchts23/canvas/2qchts23_00000054.jpg",
                "@type": "oa:SpecificResource",
                "within": {
                    "@id": "https://readux.ecdsdev.org/iiif/v2/2qchts23/manifest",
                    "@type": "sc:Manifest"
                },
                "selector": {
                    "@type": "oa:FragmentSelector",
                    "value": "xywh=1103,3968,77,22",
                    "item": {
                        "@type": "oa:FragmentSelector"
                    }
                }
            },
            "stylesheet": {
                "type": "CssStylesheet",
                "value": ".anno-8831d304-ed55-4b6a-9326-cbea343a9d15: { height: 22px; width: 77px; font-size: 13.75px; letter-spacing: 70.125px;}"
            }
        },
        {
            "@context": "http://iiif.io/api/presentation/2/context.json",
            "@id": "06e23406-7543-42df-ad42-b1f6381218ab",
            "@type": "oa:Annotation",
            "motivation": "sc:painting",
            "annotatedBy": {
                "name": "OCR"
            },
            "resource": {
                "@type": "cnt:ContentAsText",
                "format": "text/html",
                "chars": "<span id='06e23406-7543-42df-ad42-b1f6381218ab' class='anno-06e23406-7543-42df-ad42-b1f6381218ab' data-letter-spacing='-1.0222222222222224'>Laurentio</span>",
                "language": "en"
            },
            "on": {
                "full": "https://readux.ecdsdev.org/iiif/v2/2qchts23/canvas/2qchts23_00000054.jpg",
                "@type": "oa:SpecificResource",
                "within": {
                    "@id": "https://readux.ecdsdev.org/iiif/v2/2qchts23/manifest",
                    "@type": "sc:Manifest"
                },
                "selector": {
                    "@type": "oa:FragmentSelector",
                    "value": "xywh=1103,4013,75,272",
                    "item": {
                        "@type": "oa:FragmentSelector"
                    }
                }
            },
            "stylesheet": {
                "type": "CssStylesheet",
                "value": ".anno-06e23406-7543-42df-ad42-b1f6381218ab: { height: 272px; width: 75px; font-size: 170.0px; letter-spacing: -76.66666666666667px;}"
            }
        },
        {
            "@context": "http://iiif.io/api/presentation/2/context.json",
            "@id": "ed97ccee-8c79-457c-b76b-25561df4d34d",
            "@type": "oa:Annotation",
            "motivation": "sc:painting",
            "annotatedBy": {
                "name": "OCR"
            },
            "resource": {
                "@type": "cnt:ContentAsText",
                "format": "text/html",
                "chars": "<span id='ed97ccee-8c79-457c-b76b-25561df4d34d' class='anno-ed97ccee-8c79-457c-b76b-25561df4d34d' data-letter-spacing='-0.9082792207792207'>Bernino</span>",
                "language": "en"
            },
            "on": {
                "full": "https://readux.ecdsdev.org/iiif/v2/2qchts23/canvas/2qchts23_00000054.jpg",
                "@type": "oa:SpecificResource",
                "within": {
                    "@id": "https://readux.ecdsdev.org/iiif/v2/2qchts23/manifest",
                    "@type": "sc:Manifest"
                },
                "selector": {
                    "@type": "oa:FragmentSelector",
                    "value": "xywh=1105,4328,77,259",
                    "item": {
                        "@type": "oa:FragmentSelector"
                    }
                }
            },
            "stylesheet": {
                "type": "CssStylesheet",
                "value": ".anno-ed97ccee-8c79-457c-b76b-25561df4d34d: { height: 259px; width: 77px; font-size: 161.875px; letter-spacing: -69.9375px;}"
            }
        },
        {
            "@context": "http://iiif.io/api/presentation/2/context.json",
            "@id": "60d4ab68-c9d1-4f92-841a-ebdb79ef0b47",
            "@type": "oa:Annotation",
            "motivation": "sc:painting",
            "annotatedBy": {
                "name": "OCR"
            },
            "resource": {
                "@type": "cnt:ContentAsText",
                "format": "text/html",
                "chars": "<span id='60d4ab68-c9d1-4f92-841a-ebdb79ef0b47' class='anno-60d4ab68-c9d1-4f92-841a-ebdb79ef0b47' data-letter-spacing='-0.27631578947368424'>Arch</span>",
                "language": "en"
            },
            "on": {
                "full": "https://readux.ecdsdev.org/iiif/v2/2qchts23/canvas/2qchts23_00000054.jpg",
                "@type": "oa:SpecificResource",
                "within": {
                    "@id": "https://readux.ecdsdev.org/iiif/v2/2qchts23/manifest",
                    "@type": "sc:Manifest"
                },
                "selector": {
                    "@type": "oa:FragmentSelector",
                    "value": "xywh=1106,4631,76,128",
                    "item": {
                        "@type": "oa:FragmentSelector"
                    }
                }
            },
            "stylesheet": {
                "type": "CssStylesheet",
                "value": ".anno-60d4ab68-c9d1-4f92-841a-ebdb79ef0b47: { height: 128px; width: 76px; font-size: 80.0px; letter-spacing: -21.0px;}"
            }
        },
        {
            "@context": "http://iiif.io/api/presentation/2/context.json",
            "@id": "b950927b-ecc3-45f8-b92b-611d33cde347",
            "@type": "oa:Annotation",
            "motivation": "sc:painting",
            "annotatedBy": {
                "name": "OCR"
            },
            "resource": {
                "@type": "cnt:ContentAsText",
                "format": "text/html",
                "chars": "<span id='b950927b-ecc3-45f8-b92b-611d33cde347' class='anno-b950927b-ecc3-45f8-b92b-611d33cde347' data-letter-spacing='0.9095394736842105'>.</span>",
                "language": "en"
            },
            "on": {
                "full": "https://readux.ecdsdev.org/iiif/v2/2qchts23/canvas/2qchts23_00000054.jpg",
                "@type": "oa:SpecificResource",
                "within": {
                    "@id": "https://readux.ecdsdev.org/iiif/v2/2qchts23/manifest",
                    "@type": "sc:Manifest"
                },
                "selector": {
                    "@type": "oa:FragmentSelector",
                    "value": "xywh=1106,4778,76,22",
                    "item": {
                        "@type": "oa:FragmentSelector"
                    }
                }
            },
            "stylesheet": {
                "type": "CssStylesheet",
                "value": ".anno-b950927b-ecc3-45f8-b92b-611d33cde347: { height: 22px; width: 76px; font-size: 13.75px; letter-spacing: 69.125px;}"
            }
        },
        {
            "@context": "http://iiif.io/api/presentation/2/context.json",
            "@id": "ba5c520d-51a3-48fd-afcc-724988ee451e",
            "@type": "oa:Annotation",
            "motivation": "sc:painting",
            "annotatedBy": {
                "name": "OCR"
            },
            "resource": {
                "@type": "cnt:ContentAsText",
                "format": "text/html",
                "chars": "<span id='ba5c520d-51a3-48fd-afcc-724988ee451e' class='anno-ba5c520d-51a3-48fd-afcc-724988ee451e' data-letter-spacing='0.931640625'>4</span>",
                "language": "en"
            },
            "on": {
                "full": "https://readux.ecdsdev.org/iiif/v2/2qchts23/canvas/2qchts23_00000054.jpg",
                "@type": "oa:SpecificResource",
                "within": {
                    "@id": "https://readux.ecdsdev.org/iiif/v2/2qchts23/manifest",
                    "@type": "sc:Manifest"
                },
                "selector": {
                    "@type": "oa:FragmentSelector",
                    "value": "xywh=1325,5186,64,14",
                    "item": {
                        "@type": "oa:FragmentSelector"
                    }
                }
            },
            "stylesheet": {
                "type": "CssStylesheet",
                "value": ".anno-ba5c520d-51a3-48fd-afcc-724988ee451e: { height: 14px; width: 64px; font-size: 8.75px; letter-spacing: 59.625px;}"
            }
        },
        {
            "@context": "http://iiif.io/api/presentation/2/context.json",
            "@id": "bd64406f-da7f-47b2-b166-70373609293f",
            "@type": "oa:Annotation",
            "motivation": "sc:painting",
            "annotatedBy": {
                "name": "OCR"
            },
            "resource": {
                "@type": "cnt:ContentAsText",
                "format": "text/html",
                "chars": "<span id='bd64406f-da7f-47b2-b166-70373609293f' class='anno-bd64406f-da7f-47b2-b166-70373609293f' data-letter-spacing='-0.02364864864864865'>60</span>",
                "language": "en"
            },
            "on": {
                "full": "https://readux.ecdsdev.org/iiif/v2/2qchts23/canvas/2qchts23_00000054.jpg",
                "@type": "oa:SpecificResource",
                "within": {
                    "@id": "https://readux.ecdsdev.org/iiif/v2/2qchts23/manifest",
                    "@type": "sc:Manifest"
                },
                "selector": {
                    "@type": "oa:FragmentSelector",
                    "value": "xywh=1260,5175,37,62",
                    "item": {
                        "@type": "oa:FragmentSelector"
                    }
                }
            },
            "stylesheet": {
                "type": "CssStylesheet",
                "value": ".anno-bd64406f-da7f-47b2-b166-70373609293f: { height: 62px; width: 37px; font-size: 38.75px; letter-spacing: -0.875px;}"
            }
        },
        {
            "@context": "http://iiif.io/api/presentation/2/context.json",
            "@id": "fa0b08dc-5c7d-4c71-84b5-fab4b5c8bbb9",
            "@type": "oa:Annotation",
            "motivation": "sc:painting",
            "annotatedBy": {
                "name": "OCR"
            },
            "resource": {
                "@type": "cnt:ContentAsText",
                "format": "text/html",
                "chars": "<span id='fa0b08dc-5c7d-4c71-84b5-fab4b5c8bbb9' class='anno-fa0b08dc-5c7d-4c71-84b5-fab4b5c8bbb9' data-letter-spacing='0.9172794117647058'>5</span>",
                "language": "en"
            },
            "on": {
                "full": "https://readux.ecdsdev.org/iiif/v2/2qchts23/canvas/2qchts23_00000054.jpg",
                "@type": "oa:SpecificResource",
                "within": {
                    "@id": "https://readux.ecdsdev.org/iiif/v2/2qchts23/manifest",
                    "@type": "sc:Manifest"
                },
                "selector": {
                    "@type": "oa:FragmentSelector",
                    "value": "xywh=1248,3566,34,9",
                    "item": {
                        "@type": "oa:FragmentSelector"
                    }
                }
            },
            "stylesheet": {
                "type": "CssStylesheet",
                "value": ".anno-fa0b08dc-5c7d-4c71-84b5-fab4b5c8bbb9: { height: 9px; width: 34px; font-size: 5.625px; letter-spacing: 31.1875px;}"
            }
        },
        {
            "@context": "http://iiif.io/api/presentation/2/context.json",
            "@id": "b832b9f2-1921-4a2f-a6bf-9f0ba9e0a518",
            "@type": "oa:Annotation",
            "motivation": "sc:painting",
            "annotatedBy": {
                "name": "OCR"
            },
            "resource": {
                "@type": "cnt:ContentAsText",
                "format": "text/html",
                "chars": "<span id='b832b9f2-1921-4a2f-a6bf-9f0ba9e0a518' class='anno-b832b9f2-1921-4a2f-a6bf-9f0ba9e0a518' data-letter-spacing='0.13541666666666666'>10</span>",
                "language": "en"
            },
            "on": {
                "full": "https://readux.ecdsdev.org/iiif/v2/2qchts23/canvas/2qchts23_00000054.jpg",
                "@type": "oa:SpecificResource",
                "within": {
                    "@id": "https://readux.ecdsdev.org/iiif/v2/2qchts23/manifest",
                    "@type": "sc:Manifest"
                },
                "selector": {
                    "@type": "oa:FragmentSelector",
                    "value": "xywh=1244,3707,30,35",
                    "item": {
                        "@type": "oa:FragmentSelector"
                    }
                }
            },
            "stylesheet": {
                "type": "CssStylesheet",
                "value": ".anno-b832b9f2-1921-4a2f-a6bf-9f0ba9e0a518: { height: 35px; width: 30px; font-size: 21.875px; letter-spacing: 4.0625px;}"
            }
        },
        {
            "@context": "http://iiif.io/api/presentation/2/context.json",
            "@id": "8a7c901e-8bca-481d-b8a8-7ea3752604d4",
            "@type": "oa:Annotation",
            "motivation": "sc:painting",
            "annotatedBy": {
                "name": "OCR"
            },
            "resource": {
                "@type": "cnt:ContentAsText",
                "format": "text/html",
                "chars": "<span id='8a7c901e-8bca-481d-b8a8-7ea3752604d4' class='anno-8a7c901e-8bca-481d-b8a8-7ea3752604d4' data-letter-spacing='0.03125'>20</span>",
                "language": "en"
            },
            "on": {
                "full": "https://readux.ecdsdev.org/iiif/v2/2qchts23/canvas/2qchts23_00000054.jpg",
                "@type": "oa:SpecificResource",
                "within": {
                    "@id": "https://readux.ecdsdev.org/iiif/v2/2qchts23/manifest",
                    "@type": "sc:Manifest"
                },
                "selector": {
                    "@type": "oa:FragmentSelector",
                    "value": "xywh=1255,3991,38,57",
                    "item": {
                        "@type": "oa:FragmentSelector"
                    }
                }
            },
            "stylesheet": {
                "type": "CssStylesheet",
                "value": ".anno-8a7c901e-8bca-481d-b8a8-7ea3752604d4: { height: 57px; width: 38px; font-size: 35.625px; letter-spacing: 1.1875px;}"
            }
        },
        {
            "@context": "http://iiif.io/api/presentation/2/context.json",
            "@id": "ed267e60-d47e-477b-884a-f2a0f2d395cd",
            "@type": "oa:Annotation",
            "motivation": "sc:painting",
            "annotatedBy": {
                "name": "OCR"
            },
            "resource": {
                "@type": "cnt:ContentAsText",
                "format": "text/html",
                "chars": "<span id='ed267e60-d47e-477b-884a-f2a0f2d395cd' class='anno-ed267e60-d47e-477b-884a-f2a0f2d395cd' data-letter-spacing='0.07465277777777778'>30</span>",
                "language": "en"
            },
            "on": {
                "full": "https://readux.ecdsdev.org/iiif/v2/2qchts23/canvas/2qchts23_00000054.jpg",
                "@type": "oa:SpecificResource",
                "within": {
                    "@id": "https://readux.ecdsdev.org/iiif/v2/2qchts23/manifest",
                    "@type": "sc:Manifest"
                },
                "selector": {
                    "@type": "oa:FragmentSelector",
                    "value": "xywh=1255,4294,36,49",
                    "item": {
                        "@type": "oa:FragmentSelector"
                    }
                }
            },
            "stylesheet": {
                "type": "CssStylesheet",
                "value": ".anno-ed267e60-d47e-477b-884a-f2a0f2d395cd: { height: 49px; width: 36px; font-size: 30.625px; letter-spacing: 2.6875px;}"
            }
        },
        {
            "@context": "http://iiif.io/api/presentation/2/context.json",
            "@id": "2ba0ce6b-648e-4051-9f8c-c0ff5fc352b4",
            "@type": "oa:Annotation",
            "motivation": "sc:painting",
            "annotatedBy": {
                "name": "OCR"
            },
            "resource": {
                "@type": "cnt:ContentAsText",
                "format": "text/html",
                "chars": "<span id='2ba0ce6b-648e-4051-9f8c-c0ff5fc352b4' class='anno-2ba0ce6b-648e-4051-9f8c-c0ff5fc352b4' data-letter-spacing='0.09441489361702128'>40</span>",
                "language": "en"
            },
            "on": {
                "full": "https://readux.ecdsdev.org/iiif/v2/2qchts23/canvas/2qchts23_00000054.jpg",
                "@type": "oa:SpecificResource",
                "within": {
                    "@id": "https://readux.ecdsdev.org/iiif/v2/2qchts23/manifest",
                    "@type": "sc:Manifest"
                },
                "selector": {
                    "@type": "oa:FragmentSelector",
                    "value": "xywh=1257,4583,47,61",
                    "item": {
                        "@type": "oa:FragmentSelector"
                    }
                }
            },
            "stylesheet": {
                "type": "CssStylesheet",
                "value": ".anno-2ba0ce6b-648e-4051-9f8c-c0ff5fc352b4: { height: 61px; width: 47px; font-size: 38.125px; letter-spacing: 4.4375px;}"
            }
        },
        {
            "@context": "http://iiif.io/api/presentation/2/context.json",
            "@id": "861d0794-8367-4213-902f-00fd65c10fb6",
            "@type": "oa:Annotation",
            "motivation": "sc:painting",
            "annotatedBy": {
                "name": "OCR"
            },
            "resource": {
                "@type": "cnt:ContentAsText",
                "format": "text/html",
                "chars": "<span id='861d0794-8367-4213-902f-00fd65c10fb6' class='anno-861d0794-8367-4213-902f-00fd65c10fb6' data-letter-spacing='0.04044117647058824'>50</span>",
                "language": "en"
            },
            "on": {
                "full": "https://readux.ecdsdev.org/iiif/v2/2qchts23/canvas/2qchts23_00000054.jpg",
                "@type": "oa:SpecificResource",
                "within": {
                    "@id": "https://readux.ecdsdev.org/iiif/v2/2qchts23/manifest",
                    "@type": "sc:Manifest"
                },
                "selector": {
                    "@type": "oa:FragmentSelector",
                    "value": "xywh=1255,4887,34,50",
                    "item": {
                        "@type": "oa:FragmentSelector"
                    }
                }
            },
            "stylesheet": {
                "type": "CssStylesheet",
                "value": ".anno-861d0794-8367-4213-902f-00fd65c10fb6: { height: 50px; width: 34px; font-size: 31.25px; letter-spacing: 1.375px;}"
            }
        },
        {
            "@context": "http://iiif.io/api/presentation/2/context.json",
            "@id": "4abef6a5-8a7c-4536-90cf-d36106ab5a81",
            "@type": "oa:Annotation",
            "motivation": "sc:painting",
            "annotatedBy": {
                "name": "OCR"
            },
            "resource": {
                "@type": "cnt:ContentAsText",
                "format": "text/html",
                "chars": "<span id='4abef6a5-8a7c-4536-90cf-d36106ab5a81' class='anno-4abef6a5-8a7c-4536-90cf-d36106ab5a81' data-letter-spacing='-0.1640625'>25</span>",
                "language": "en"
            },
            "on": {
                "full": "https://readux.ecdsdev.org/iiif/v2/2qchts23/canvas/2qchts23_00000054.jpg",
                "@type": "oa:SpecificResource",
                "within": {
                    "@id": "https://readux.ecdsdev.org/iiif/v2/2qchts23/manifest",
                    "@type": "sc:Manifest"
                },
                "selector": {
                    "@type": "oa:FragmentSelector",
                    "value": "xywh=1180,7195,48,102",
                    "item": {
                        "@type": "oa:FragmentSelector"
                    }
                }
            },
            "stylesheet": {
                "type": "CssStylesheet",
                "value": ".anno-4abef6a5-8a7c-4536-90cf-d36106ab5a81: { height: 102px; width: 48px; font-size: 63.75px; letter-spacing: -7.875px;}"
            }
        },
        {
            "@context": "http://iiif.io/api/presentation/2/context.json",
            "@id": "6faecf6b-582f-4076-93e8-ca85175c26a1",
            "@type": "oa:Annotation",
            "motivation": "sc:painting",
            "annotatedBy": {
                "name": "OCR"
            },
            "resource": {
                "@type": "cnt:ContentAsText",
                "format": "text/html",
                "chars": "<span id='6faecf6b-582f-4076-93e8-ca85175c26a1' class='anno-6faecf6b-582f-4076-93e8-ca85175c26a1' data-letter-spacing='-1.418640350877193'>Laurentius</span>",
                "language": "en"
            },
            "on": {
                "full": "https://readux.ecdsdev.org/iiif/v2/2qchts23/canvas/2qchts23_00000054.jpg",
                "@type": "oa:SpecificResource",
                "within": {
                    "@id": "https://readux.ecdsdev.org/iiif/v2/2qchts23/manifest",
                    "@type": "sc:Manifest"
                },
                "selector": {
                    "@type": "oa:FragmentSelector",
                    "value": "xywh=1087,1333,57,277",
                    "item": {
                        "@type": "oa:FragmentSelector"
                    }
                }
            },
            "stylesheet": {
                "type": "CssStylesheet",
                "value": ".anno-6faecf6b-582f-4076-93e8-ca85175c26a1: { height: 277px; width: 57px; font-size: 173.125px; letter-spacing: -80.8625px;}"
            }
        },
        {
            "@context": "http://iiif.io/api/presentation/2/context.json",
            "@id": "fad62777-4bce-4bdb-b36a-52b1614160b5",
            "@type": "oa:Annotation",
            "motivation": "sc:painting",
            "annotatedBy": {
                "name": "OCR"
            },
            "resource": {
                "@type": "cnt:ContentAsText",
                "format": "text/html",
                "chars": "<span id='fad62777-4bce-4bdb-b36a-52b1614160b5' class='anno-fad62777-4bce-4bdb-b36a-52b1614160b5' data-letter-spacing='-0.45723684210526316'>Nuuo</span>",
                "language": "en"
            },
            "on": {
                "full": "https://readux.ecdsdev.org/iiif/v2/2qchts23/canvas/2qchts23_00000054.jpg",
                "@type": "oa:SpecificResource",
                "within": {
                    "@id": "https://readux.ecdsdev.org/iiif/v2/2qchts23/manifest",
                    "@type": "sc:Manifest"
                },
                "selector": {
                    "@type": "oa:FragmentSelector",
                    "value": "xywh=1085,1637,57,129",
                    "item": {
                        "@type": "oa:FragmentSelector"
                    }
                }
            },
            "stylesheet": {
                "type": "CssStylesheet",
                "value": ".anno-fad62777-4bce-4bdb-b36a-52b1614160b5: { height: 129px; width: 57px; font-size: 80.625px; letter-spacing: -26.0625px;}"
            }
        },
        {
            "@context": "http://iiif.io/api/presentation/2/context.json",
            "@id": "104aded2-1f29-45c0-ad52-a8c4a6071b97",
            "@type": "oa:Annotation",
            "motivation": "sc:painting",
            "annotatedBy": {
                "name": "OCR"
            },
            "resource": {
                "@type": "cnt:ContentAsText",
                "format": "text/html",
                "chars": "<span id='104aded2-1f29-45c0-ad52-a8c4a6071b97' class='anno-104aded2-1f29-45c0-ad52-a8c4a6071b97' data-letter-spacing='-0.18859649122807018'>lone</span>",
                "language": "en"
            },
            "on": {
                "full": "https://readux.ecdsdev.org/iiif/v2/2qchts23/canvas/2qchts23_00000054.jpg",
                "@type": "oa:SpecificResource",
                "within": {
                    "@id": "https://readux.ecdsdev.org/iiif/v2/2qchts23/manifest",
                    "@type": "sc:Manifest"
                },
                "selector": {
                    "@type": "oa:FragmentSelector",
                    "value": "xywh=1085,1777,57,80",
                    "item": {
                        "@type": "oa:FragmentSelector"
                    }
                }
            },
            "stylesheet": {
                "type": "CssStylesheet",
                "value": ".anno-104aded2-1f29-45c0-ad52-a8c4a6071b97: { height: 80px; width: 57px; font-size: 50.0px; letter-spacing: -10.75px;}"
            }
        },
        {
            "@context": "http://iiif.io/api/presentation/2/context.json",
            "@id": "165ea574-a4a5-4e36-a479-d8ab921d8ae3",
            "@type": "oa:Annotation",
            "motivation": "sc:painting",
            "annotatedBy": {
                "name": "OCR"
            },
            "resource": {
                "@type": "cnt:ContentAsText",
                "format": "text/html",
                "chars": "<span id='165ea574-a4a5-4e36-a479-d8ab921d8ae3' class='anno-165ea574-a4a5-4e36-a479-d8ab921d8ae3' data-letter-spacing='-0.337280701754386'>delin</span>",
                "language": "en"
            },
            "on": {
                "full": "https://readux.ecdsdev.org/iiif/v2/2qchts23/canvas/2qchts23_00000054.jpg",
                "@type": "oa:SpecificResource",
                "within": {
                    "@id": "https://readux.ecdsdev.org/iiif/v2/2qchts23/manifest",
                    "@type": "sc:Manifest"
                },
                "selector": {
                    "@type": "oa:FragmentSelector",
                    "value": "xywh=1085,1902,57,98",
                    "item": {
                        "@type": "oa:FragmentSelector"
                    }
                }
            },
            "stylesheet": {
                "type": "CssStylesheet",
                "value": ".anno-165ea574-a4a5-4e36-a479-d8ab921d8ae3: { height: 98px; width: 57px; font-size: 61.25px; letter-spacing: -19.225px;}"
            }
        },
        {
            "@context": "http://iiif.io/api/presentation/2/context.json",
            "@id": "eeae8f6c-2912-4093-9b0b-91650049ed5d",
            "@type": "oa:Annotation",
            "motivation": "sc:painting",
            "annotatedBy": {
                "name": "OCR"
            },
            "resource": {
                "@type": "cnt:ContentAsText",
                "format": "text/html",
                "chars": "<span id='eeae8f6c-2912-4093-9b0b-91650049ed5d' class='anno-eeae8f6c-2912-4093-9b0b-91650049ed5d' data-letter-spacing='0.9232456140350878'>.</span>",
                "language": "en"
            },
            "on": {
                "full": "https://readux.ecdsdev.org/iiif/v2/2qchts23/canvas/2qchts23_00000054.jpg",
                "@type": "oa:SpecificResource",
                "within": {
                    "@id": "https://readux.ecdsdev.org/iiif/v2/2qchts23/manifest",
                    "@type": "sc:Manifest"
                },
                "selector": {
                    "@type": "oa:FragmentSelector",
                    "value": "xywh=1085,2022,57,14",
                    "item": {
                        "@type": "oa:FragmentSelector"
                    }
                }
            },
            "stylesheet": {
                "type": "CssStylesheet",
                "value": ".anno-eeae8f6c-2912-4093-9b0b-91650049ed5d: { height: 14px; width: 57px; font-size: 8.75px; letter-spacing: 52.625px;}"
            }
        }
    ]
}